{"noiseKey":{"private":{"type":"Buffer","data":"gNsdAdtR3Hbf3ceAcl5FBD0yfQSONDtGprEtUCnZK24="},"public":{"type":"Buffer","data":"fIKK5YQCpYSSSVyZLu6ppRGPKt2seY17rz+w5bTJeRY="}},"pairingEphemeralKeyPair":{"private":{"type":"Buffer","data":"kIykPY9aeeyXiJ0TGIjWXHZb60rrpawALO+xh98/8Gw="},"public":{"type":"Buffer","data":"5H14WU0C6yzk6YyGs0CbuVKNflGY8IalyH2yFmIDNh8="}},"signedIdentityKey":{"private":{"type":"Buffer","data":"uFILmUa4PWNZqXg/Rh5V3AasPVKm/id1zLkU3wyMw0s="},"public":{"type":"Buffer","data":"Jw4GEQkrZfxMyaLVweHXc9pzPYwJLfgIND+sYyfWUx8="}},"signedPreKey":{"keyPair":{"private":{"type":"Buffer","data":"IGbrUFEzr+7YJ3guQvL1UYC3mJ5OyhpPJvlzTOxfGWw="},"public":{"type":"Buffer","data":"6Q6fhVbKgJPzbAikEWwCpV1zwYE1FuCR1GJPzCwMQFQ="}},"signature":{"type":"Buffer","data":"y7lqQ/GYVgzeGoKeQLMJc2MLrzwErdPTOSqxBRXWt8CgCfz1CB+WEk5UTkECBhR7ixM6/wk5YGGCgpZ6d1jWjg=="},"keyId":1},"registrationId":161,"advSecretKey":"pjhr9m+7IEX54bkoJANVCocjCxrC6KRKvivgAMUaCqM=","processedHistoryMessages":[{"key":{"remoteJid":"923464323408@s.whatsapp.net","fromMe":true,"id":"3A10E425427702149E45"},"messageTimestamp":1753290565},{"key":{"remoteJid":"923464323408@s.whatsapp.net","fromMe":true,"id":"3A05EB62526518B21CD3"},"messageTimestamp":1753290570},{"key":{"remoteJid":"923464323408@s.whatsapp.net","fromMe":true,"id":"3A3B622E18F4DE0B2054"},"messageTimestamp":1753290814},{"key":{"remoteJid":"923464323408@s.whatsapp.net","fromMe":true,"id":"3A717D8917E10CE27A56"},"messageTimestamp":1753298593}],"nextPreKeyId":120,"firstUnuploadedPreKeyId":120,"accountSyncCounter":1,"accountSettings":{"unarchiveChats":false},"deviceId":"enyZjMxBT2GEU7SELKQfPw","phoneId":"34a6269d-2d32-467e-bae0-e30d27f6e115","identityId":{"type":"Buffer","data":"QKGK0HfrkEf+OIXaIczbOS3rw0Y="},"registered":true,"backupToken":{"type":"Buffer","data":"KNl/G+584YecfDkAtuToqgnhINw="},"registration":{},"pairingCode":"1DQA7C3S","me":{"id":"923464323408:2@s.whatsapp.net","name":"ALONE R.K","lid":"80063106179310:2@lid"},"account":{"details":"CKfdqdMIEK6uhMQGGAIgACgA","accountSignatureKey":"lPRzeDVsF9BjGtqCVbsXRO9ppL+EJ/1VHgiV63n2RW0=","accountSignature":"6fu7pjcV3LL7WMe3TRHv1nqTUByTUnXOIulZzGeI2QNLoh8ugtMAw30k1GXVnwaNzvm5UVM5Pz1/ARchw1q0AA==","deviceSignature":"OyM4tCCzCgzZlJpiOSben8AI0+Qf0kUweRrF8YBNLc/RWbx6A3Kds1nTXh6fHu7EgU0vL/xbYbXksCMAct+ogQ=="},"signalIdentities":[{"identifier":{"name":"923464323408:2@s.whatsapp.net","deviceId":0},"identifierKey":{"type":"Buffer","data":"BZT0c3g1bBfQYxraglW7F0TvaaS/hCf9VR4Ilet59kVt"}}],"platform":"smbi","routingInfo":{"type":"Buffer","data":"CBIIDQ=="},"lastAccountSyncTimestamp":1753299142,"lastPropHash":"2V77qU","myAppStateKeyId":"AAAAAKYE"}